{
 "type": "1",
 "title": "Archivos relacionados con la estructura de los datos",
 "description": "Archivos relacionados con la estructura de los datos.",
 "printDescription": "Página para imprimir que muestra los archivos relacionados con la estructura de los datos.",
 "listado": [
  {
   "name": "m04SuscripcionPhp.html",
   "title": "srv / modelo / suscripcion.php",
   "description": "Código de «srv/modelo/suscripcion.php»."
  },
  {
   "name": "m05bdCreaPhp.html",
   "title": "srv / dao / bdCrea.php",
   "description": "Código de «srv/dao/bdCrea.php»."
  },
  {
   "name": "m06AccesoBdPhp.html",
   "title": "srv / dao / accesobd.php",
   "description": "Código de «srv/dao/accesobd.php»."
  },
  {
   "name": "m07suscripcionAgregaPhp.html",
   "title": "srv / dao / suscripcionAgrega.php",
   "description": "Código de «srv/dao/suscripcionAgrega.php»."
  },
  {
   "name": "m08suscripcionBuscaPhp.html",
   "title": "srv / dao / suscripcionBusca.php",
   "description": "Código de «srv/dao/suscripcionBusca.php»."
  },
  {
   "name": "m09suscripcionConsultaPhp.html",
   "title": "srv / dao / suscripcionConsulta.php",
   "description": "Código de «srv/dao/suscripcionConsulta.php»."
  },
  {
   "name": "m10suscripcionEliminaPhp.html",
   "title": "srv / dao / suscripcionElimina.php",
   "description": "Código de «srv/dao/suscripcionElimina.php»."
  },
  {
   "name": "m11suscripcionModificaPhp.html",
   "title": "srv / dao / suscripcionModifica.php",
   "description": "Código de «srv/dao/suscripcionModifica.php»."
  }
 ]
}